visdom_helper/__init__.py
visdom_helper/test_visdom_helper.py
visdom_helper/visdom_helper.py
visdom_helper-0.0.1.dist-info/METADATA
visdom_helper-0.0.1.dist-info/RECORD
visdom_helper-0.0.1.dist-info/WHEEL
visdom_helper-0.0.1.dist-info/top_level.txt
