Metadata-Version: 2.1
Name: visdom-helper
Version: 0.0.1
Summary: A plotting helper for facebook visdom dashboards
Home-page: https://github.com/episodeyang/visdom_helper
Author: Ge Yang
Author-email: yangge1987@gmail.com
License: UNKNOWN
Keywords: visdom_helper,deep learning,dashboard,data dashboard,visualization
Platform: UNKNOWN
Classifier: Development Status :: 4 - Beta
Classifier: Intended Audience :: Science/Research
Classifier: Programming Language :: Python :: 3
Requires-Dist: waterbear
Requires-Dist: argparse
Requires-Dist: typing
